PetchouApps/.DS_Store
PetchouApps/__main__.py
PetchouApps/assets/back.png
PetchouApps/assets/black.png
PetchouApps/assets/mainIcon.png
PetchouApps/assets/morpionIcon.png
PetchouApps/assets/pythonLogo.png
petchouapps-0.1.1.dist-info/WHEEL
petchouapps-0.1.1.dist-info/METADATA
petchouapps-0.1.1.dist-info/RECORD
