Metadata-Version: 2.1
Name: petchouapps
Version: 0.1.1
Summary: 
Author: PetchouHelper
Author-email: petchou91d@gmail.com
Requires-Python: >=3.9,<4.0
Classifier: Programming Language :: Python :: 3
Classifier: Programming Language :: Python :: 3.9
Requires-Dist: Kivy (>=2.0.0,<3.0.0)
